Metadata-Version: 1.0
Name: Jigglypuff
Version: 0.2
Summary: Python package for creating a Risk Based Analysis Model
Home-page: https://github.com/hana-am/Jigglypuff
Author: Hana AlMashari
Author-email: hanaahmad.m@gmail.com
License: MIT
Platform: UNKNOWN
